README.md
setup.cfg
setup.py
keras_rl.egg-info/PKG-INFO
keras_rl.egg-info/SOURCES.txt
keras_rl.egg-info/dependency_links.txt
keras_rl.egg-info/requires.txt
keras_rl.egg-info/top_level.txt
rl/__init__.py
rl/callbacks.py
rl/core.py
rl/memory.py
rl/policy.py
rl/processors.py
rl/random.py
rl/util.py
rl/agents/__init__.py
rl/agents/async.py
rl/agents/cem.py
rl/agents/ddpg.py
rl/agents/dqn.py
rl/agents/sarsa.py
tests/__init__.py
tests/rl/__init__.py
tests/rl/test_core.py
tests/rl/test_memory.py
tests/rl/test_util.py
tests/rl/util.py
tests/rl/agents/__init__.py
tests/rl/agents/test_cem.py
tests/rl/agents/test_ddpg.py
tests/rl/agents/test_dqn.py