Metadata-Version: 1.1
Name: keras-rl
Version: 0.4.0
Summary: Deep Reinforcement Learning for Keras
Home-page: https://github.com/matthiasplappert/keras-rl
Author: Matthias Plappert
Author-email: matthiasplappert@me.com
License: MIT
Download-URL: https://github.com/matthiasplappert/keras-rl/archive/v0.4.0.tar.gz
Platform: UNKNOWN
